deez_stats/__init__.py
deez_stats/league_info.py
deez_stats/leagueinfo.py
deez_stats/manager_info.py
deez_stats/managerinfo.py
deez_stats/matchup_history.py
deez_stats/player_info.py
deez_stats/playerinfo.py
deez_stats/standings.py
deez_stats/transaction_info.py
deez_stats/weekly_matchup.py
deez_stats/helpers/__init__.py
deez_stats/helpers/database_query.py
deez_stats/helpers/elo_test.py
deez_stats/helpers/json_query.py
deez_stats/helpers/simple_stats.py
deez_stats/helpers/telo.py
deez_stats/helpers/webtools.py
deez_stats/helpers/files/constitution.md
deez_stats/helpers/files/yahoo_api_nonsense.md
deez_stats/helpers/files/database/history.db
deez_stats/helpers/files/json/cleaned_names.json
deez_stats/helpers/files/json/game_league_ids.json
deez_stats-0.2.16.dist-info/LICENSE
deez_stats-0.2.16.dist-info/METADATA
deez_stats-0.2.16.dist-info/WHEEL
deez_stats-0.2.16.dist-info/top_level.txt
deez_stats-0.2.16.dist-info/RECORD
