Metadata-Version: 2.1
Name: deez-stats
Version: 0.2.16
Summary: Python bindings to access competitive league stats.
Home-page: https://github.com/salty-spitoon/deez_stats
Author: Tom Brady
Author-email: bradyte@gmail.com
License: MIT
Platform: UNKNOWN
Classifier: Development Status :: 4 - Beta
Classifier: Intended Audience :: Developers
Classifier: License :: OSI Approved :: MIT License
Classifier: Programming Language :: Python :: 3
Requires-Python: >=3.7.1,<3.11
License-File: LICENSE
Requires-Dist: objectpath
Requires-Dist: yahoo-fantasy-api
Requires-Dist: yahoo-oauth
Requires-Dist: numpy
Requires-Dist: pandas
